MANIFEST.in
README.rst
distribute_setup.py
requirements.txt
setup.py
Glastopf.egg-info/PKG-INFO
Glastopf.egg-info/SOURCES.txt
Glastopf.egg-info/dependency_links.txt
Glastopf.egg-info/requires.txt
Glastopf.egg-info/top_level.txt
bin/glastopf-runner
glastopf/__init__.py
glastopf/glastopf.cfg.dist
glastopf/glastopf.py
glastopf/requests.xml
glastopf/wsgi_wrapper.py
glastopf/modules/__init__.py
glastopf/modules/logging_handler.py
glastopf/modules/privileges.py
glastopf/modules/vdocs.py
glastopf/modules/HTTP/__init__.py
glastopf/modules/HTTP/handler.py
glastopf/modules/HTTP/method_handler.py
glastopf/modules/classification/__init__.py
glastopf/modules/classification/request.py
glastopf/modules/classification/sql.py
glastopf/modules/classification/sql_utils/__init__.py
glastopf/modules/classification/sql_utils/patterns.xml
glastopf/modules/classification/sql_utils/queries.xml
glastopf/modules/classification/sql_utils/responses.py
glastopf/modules/classification/sql_utils/responses.xml
glastopf/modules/classification/sql_utils/token_map.json
glastopf/modules/classification/sql_utils/tokenizer.py
glastopf/modules/events/__init__.py
glastopf/modules/events/attack.py
glastopf/modules/handlers/__init__.py
glastopf/modules/handlers/base_emulator.py
glastopf/modules/handlers/request_handler.py
glastopf/modules/handlers/emulators/__init__.py
glastopf/modules/handlers/emulators/comments.py
glastopf/modules/handlers/emulators/dummy.py
glastopf/modules/handlers/emulators/favicon_ico.py
glastopf/modules/handlers/emulators/file_server.py
glastopf/modules/handlers/emulators/head.py
glastopf/modules/handlers/emulators/lfi.py
glastopf/modules/handlers/emulators/login.py
glastopf/modules/handlers/emulators/options.py
glastopf/modules/handlers/emulators/php_cgi_rce.py
glastopf/modules/handlers/emulators/phpinfo.py
glastopf/modules/handlers/emulators/phpmyadmin.py
glastopf/modules/handlers/emulators/rfi.py
glastopf/modules/handlers/emulators/robots.py
glastopf/modules/handlers/emulators/sqli.py
glastopf/modules/handlers/emulators/style_css.py
glastopf/modules/handlers/emulators/tomcat_manager.py
