Metadata-Version: 1.0
Name: Glastopf
Version: 3.1.2
Summary: Web application honeypot
Home-page: http://glastopf.org
Author: Glastopf Project
Author-email: glastopf@public.honeynet.org
License: GPL 3
Platform: UNKNOWN
